sty/__init__.py
sty/lib.py
sty/primitive.py
sty/py.typed
sty/register.py
sty/renderfunc.py
sty/rendertype.py
sty-1.0.5.dist-info/LICENSE
sty-1.0.5.dist-info/METADATA
sty-1.0.5.dist-info/WHEEL
sty-1.0.5.dist-info/RECORD
