Metadata-Version: 2.1
Name: sty
Version: 1.0.5
Summary: String styling for your terminal
Home-page: https://sty.mewo.dev/
License: Apache 2.0
Keywords: styling,color,colour,terminal,ansi,command,line,cli
Author: feluxe
Author-email: felix@meyerwolters.de
Maintainer: feluxe
Maintainer-email: felix@meyerwolters.de
Requires-Python: >=3.7,<4.0
Classifier: License :: Other/Proprietary License
Classifier: Operating System :: OS Independent
Classifier: Programming Language :: Python :: 3
Classifier: Programming Language :: Python :: 3.7
Classifier: Programming Language :: Python :: 3.8
Classifier: Programming Language :: Python :: 3.9
Classifier: Programming Language :: Python :: 3.10
Classifier: Programming Language :: Python :: 3.11
Classifier: Programming Language :: Python :: 3.12
Classifier: Topic :: Printing
Classifier: Topic :: System :: Shells
Classifier: Topic :: Terminals
Classifier: Typing :: Typed
Project-URL: Documentation, https://sty.mewo.dev/
Project-URL: Repository, https://github.com/feluxe/sty
